nerdynamegen/__init__.py
nerdynamegen/__main__.py
nerdynamegen/data/names.csv
nerdynamegen/data/phrases.csv
nerdynamegen/data/places.csv
nerdynamegen/dbconnsqlite.py
daedal_nerdynamegen-0.1.0.dist-info/LICENSE
daedal_nerdynamegen-0.1.0.dist-info/METADATA
daedal_nerdynamegen-0.1.0.dist-info/WHEEL
daedal_nerdynamegen-0.1.0.dist-info/entry_points.txt
daedal_nerdynamegen-0.1.0.dist-info/RECORD
