Metadata-Version: 2.3
Name: daedal-nerdynamegen
Version: 0.1.0
Summary: A nerdy name generator with SQLite database support
License: MIT
Author: Deb Mishra
Author-email: infra@daedal.org
Requires-Python: >=3.8,<4.0
Classifier: License :: OSI Approved :: MIT License
Classifier: Programming Language :: Python :: 3
Classifier: Programming Language :: Python :: 3.8
Classifier: Programming Language :: Python :: 3.9
Classifier: Programming Language :: Python :: 3.10
Classifier: Programming Language :: Python :: 3.11
Classifier: Programming Language :: Python :: 3.12
Classifier: Programming Language :: Python :: 3.13
